alphafold2_pytorch/__init__.py
alphafold2_pytorch/alphafold2.py
alphafold2_pytorch/constants.py
alphafold2_pytorch/embeds.py
alphafold2_pytorch/mlm.py
alphafold2_pytorch/reversible.py
alphafold2_pytorch/rotary.py
alphafold2_pytorch/utils.py
alphafold2_pytorch-0.4.32.dist-info/LICENSE
alphafold2_pytorch-0.4.32.dist-info/METADATA
alphafold2_pytorch-0.4.32.dist-info/WHEEL
alphafold2_pytorch-0.4.32.dist-info/top_level.txt
alphafold2_pytorch-0.4.32.dist-info/RECORD
