Metadata-Version: 2.1
Name: alphafold2-pytorch
Version: 0.4.32
Summary: AlphaFold2 - Pytorch
Home-page: https://github.com/lucidrains/alphafold2
Author: Phil Wang, Eric Alcaide
Author-email: lucidrains@gmail.com, ericalcaide1@gmail.com
License: MIT
Keywords: artificial intelligence,attention mechanism,protein folding
Platform: UNKNOWN
Classifier: Development Status :: 4 - Beta
Classifier: Intended Audience :: Developers
Classifier: Topic :: Scientific/Engineering :: Artificial Intelligence
Classifier: License :: OSI Approved :: MIT License
Classifier: Programming Language :: Python :: 3.7
License-File: LICENSE
Requires-Dist: einops (>=0.3)
Requires-Dist: En-transformer (>=0.2.3)
Requires-Dist: invariant-point-attention
Requires-Dist: mdtraj (>=1.8)
Requires-Dist: numpy
Requires-Dist: proDy
Requires-Dist: pytorch3d
Requires-Dist: requests
Requires-Dist: sidechainnet
Requires-Dist: torch (>=1.6)
Requires-Dist: transformers
Requires-Dist: tqdm
Requires-Dist: biopython
Requires-Dist: mp-nerf (>=0.1.5)
